snappyr/__init__.py
snappyr-0.1.1.dist-info/entry_points.txt
snappyr-0.1.1.dist-info/METADATA
snappyr-0.1.1.dist-info/WHEEL
snappyr-0.1.1.dist-info/RECORD
