Metadata-Version: 2.1
Name: snappyr
Version: 0.1.1
Summary: Setup Projects Blazingly Fast with Snappyr
Author: Yash Srivastava
Author-email: ysrivastava82@gmail.com
Requires-Python: >=3.11,<4.0
Classifier: Programming Language :: Python :: 3
Classifier: Programming Language :: Python :: 3.11
Classifier: Programming Language :: Python :: 3.12
